Xnode2vec
