Metadata-Version: 2.1
Name: Xnode2vec
Version: 0.11.7
Summary: Alternative method for data clustering using Node2Vec algorithm.
Home-page: https://github.com/Stefano314/XNode2Vec
Author: Stefano Bianchi
Author-email: stefanobianchi314@gmail.com
License: UNKNOWN
Platform: UNKNOWN
Classifier: Programming Language :: Python :: 3
Classifier: Topic :: Scientific/Engineering :: Artificial Intelligence
Requires-Python: >=3.6
